{"files":{"navbar.html":{"frameworks":["pg.insight.events","pg.css.grid","pg.image.overlay","pg.code-validator","pg.project.items","pg.asset.manager","bs4","pg.html","pg.components"],"last_page_width":1024},"tracker.html":{"frameworks":["www","pg.code-validator","pg.insight.events","pg.asset.manager","pg.project.items","pg.fontawesome.5","pg.css.grid","pg.image.overlay","bs4","pg.html","pg.components"],"last_page_width":1024},"index.html":{"frameworks":["RagingWolfWebsiteTemp","pg.insight.events","pg.asset.manager","pg.project.items","pg.code-validator","pg.css.grid","pg.image.overlay","bs4","pg.html","pg.components"],"last_page_width":1200},"_tracker.html":{"frameworks":["www","pg.insight.events","pg.css.grid","pg.image.overlay","pg.code-validator","pg.project.items","pg.asset.manager","bs4","pg.html","pg.components"],"last_page_width":1024},"_orders.html":{"frameworks":["www","pg.css.grid","pg.asset.manager","pg.insight.events","pg.code-validator","pg.image.overlay","pg.fontawesome.5","pg.project.items","bs4","pg.html","pg.components"],"last_page_width":1024}},"breakpoints":["576px","768px","992px","1200px"],"frameworks":["RagingWolfWebsiteTemp","pg.insight.events","pg.asset.manager","pg.project.items","pg.code-validator","pg.css.grid","pg.image.overlay","bs4","pg.html","pg.components"],"template_framework_id":"bootstrap","compiledStylesheet":{"bootstrap/css/bootstrap.css":"bootstrap_theme/custom.scss"},"useSourceStylesheet":{},"cs-for-overrides-vars":"bootstrap_theme/custom.scss","cs-for-overrides":"bootstrap_theme/custom.scss"}